{
  "week": {
    "start": "2026-07-06",
    "end": "2026-07-12",
    "label": "2026년 W28",
    "range": "07/06–07/12"
  },
  "summary": {
    "total_reports": 153,
    "avg_completion": 64,
    "active_people": 8,
    "open_decisions": 2
  },
  "teams": [
    {
      "team": "사업기획",
      "members": [
        "배성원",
        "김도영"
      ],
      "active_members": [
        "김도영",
        "배성원"
      ],
      "task_count": 45,
      "per_capita": 22.5,
      "completion_rate": 49,
      "categories": {
        "기획": 12,
        "실행": 11,
        "관리": 10,
        "커뮤니케이션": 7,
        "리서치": 3,
        "기타": 2
      },
      "common_blockers": [],
      "tools": [
        "엑셀",
        "클로드코드",
        "CAD",
        "공유폴더",
        "SketchUp",
        "한글"
      ],
      "assignment_total": 0,
      "assignment_done": 0,
      "assignment_rate": null
    },
    {
      "team": "공간팀",
      "members": [
        "전제훈",
        "김가은",
        "김예진"
      ],
      "active_members": [
        "김가은",
        "김예진"
      ],
      "task_count": 25,
      "per_capita": 12.5,
      "completion_rate": 68,
      "categories": {
        "기획": 10,
        "관리": 5,
        "커뮤니케이션": 4,
        "실행": 3,
        "리서치": 3
      },
      "common_blockers": [],
      "tools": [
        "AI"
      ],
      "assignment_total": 2,
      "assignment_done": 0,
      "assignment_rate": 0
    },
    {
      "team": "기획팀",
      "members": [
        "양지혜",
        "정예은"
      ],
      "active_members": [
        "양지혜",
        "정예은"
      ],
      "task_count": 21,
      "per_capita": 10.5,
      "completion_rate": 86,
      "categories": {
        "실행": 11,
        "커뮤니케이션": 5,
        "기획": 3,
        "리서치": 2
      },
      "common_blockers": [],
      "tools": [
        "일러스트레이터"
      ],
      "assignment_total": 0,
      "assignment_done": 0,
      "assignment_rate": null
    },
    {
      "team": "운영팀",
      "members": [
        "양은정",
        "김준호",
        "윤혜정"
      ],
      "active_members": [
        "양은정",
        "윤혜정"
      ],
      "task_count": 62,
      "per_capita": 31.0,
      "completion_rate": 67,
      "categories": {
        "커뮤니케이션": 18,
        "실행": 15,
        "기획": 12,
        "관리": 10,
        "리서치": 3,
        "기타": 3,
        "교육": 1
      },
      "common_blockers": [],
      "tools": [
        "챗지피티"
      ],
      "assignment_total": 1,
      "assignment_done": 0,
      "assignment_rate": 0
    }
  ],
  "persons": [
    {
      "name": "배성원",
      "team": "사업기획",
      "task_count": 28,
      "completion_rate": 36,
      "categories": {
        "기획": 7,
        "실행": 7,
        "관리": 7,
        "커뮤니케이션": 6,
        "리서치": 1
      },
      "blockers": [
        "현재 회사 법인카드 사용이 막혀 있어서 비용사용에 문제가 있음",
        "고위드 신용카드 사용이 되지 않는 부분 원인 찾는데 시간을 좀 허비함"
      ],
      "tools": [
        "엑셀"
      ],
      "open_decisions": [],
      "growth": {
        "status": "scored",
        "resolution": 36,
        "coverage": 50,
        "depth_avg": 2.2,
        "metrics": {
          "clarity": 2,
          "structure": 2,
          "evidence": 2,
          "output_quality": 2,
          "outcome_quality": 0,
          "decision_thinking": 0
        }
      }
    },
    {
      "name": "김도영",
      "team": "사업기획",
      "task_count": 17,
      "completion_rate": 71,
      "categories": {
        "기획": 5,
        "실행": 4,
        "관리": 3,
        "리서치": 2,
        "기타": 2,
        "커뮤니케이션": 1
      },
      "blockers": [],
      "tools": [
        "클로드코드",
        "엑셀",
        "CAD",
        "공유폴더",
        "SketchUp",
        "한글"
      ],
      "open_decisions": [],
      "growth": {
        "status": "scored",
        "resolution": 100,
        "coverage": 100,
        "depth_avg": 3.0,
        "metrics": {
          "clarity": 3,
          "structure": 3,
          "evidence": 3,
          "output_quality": 3,
          "outcome_quality": 3,
          "decision_thinking": 3
        }
      }
    },
    {
      "name": "김예진",
      "team": "공간팀",
      "task_count": 19,
      "completion_rate": 79,
      "categories": {
        "기획": 6,
        "관리": 4,
        "실행": 3,
        "커뮤니케이션": 3,
        "리서치": 3
      },
      "blockers": [],
      "tools": [
        "AI"
      ],
      "open_decisions": [],
      "growth": {
        "status": "scored",
        "resolution": 23,
        "coverage": 25,
        "depth_avg": 2.8,
        "metrics": {
          "clarity": 3,
          "structure": 3,
          "evidence": 3,
          "output_quality": 3,
          "outcome_quality": 0,
          "decision_thinking": 0
        }
      }
    },
    {
      "name": "김가은",
      "team": "공간팀",
      "task_count": 6,
      "completion_rate": 33,
      "categories": {
        "기획": 4,
        "커뮤니케이션": 1,
        "관리": 1
      },
      "blockers": [
        "없어\\"
      ],
      "tools": [],
      "open_decisions": [],
      "growth": {
        "status": "scored",
        "resolution": 22,
        "coverage": 38,
        "depth_avg": 1.8,
        "metrics": {
          "clarity": 2,
          "structure": 2,
          "evidence": 2,
          "output_quality": 2,
          "outcome_quality": 0,
          "decision_thinking": 0
        }
      }
    },
    {
      "name": "정예은",
      "team": "기획팀",
      "task_count": 11,
      "completion_rate": 100,
      "categories": {
        "실행": 5,
        "기획": 3,
        "커뮤니케이션": 3
      },
      "blockers": [
        "제작 방향 픽스 필요",
        "MASI RAW 카드뉴스 디자인 작업을 진행했다.\n\n운영팀에서 전달받은 자료를 기반으로 작업했지만, 카드뉴스"
      ],
      "tools": [],
      "open_decisions": [
        "내일 대표님께서 견적서와 도면 확인 후, 계약 진행을 꼭해야 7월 24일까지 상자들을 받을 수 있다."
      ],
      "growth": {
        "status": "scored",
        "resolution": 58,
        "coverage": 88,
        "depth_avg": 2.0,
        "metrics": {
          "clarity": 2,
          "structure": 2,
          "evidence": 2,
          "output_quality": 2,
          "outcome_quality": 0,
          "decision_thinking": 2
        }
      }
    },
    {
      "name": "양지혜",
      "team": "기획팀",
      "task_count": 10,
      "completion_rate": 70,
      "categories": {
        "실행": 6,
        "리서치": 2,
        "커뮤니케이션": 2
      },
      "blockers": [
        "cj 컨펌이 필요한 디자인"
      ],
      "tools": [
        "일러스트레이터"
      ],
      "open_decisions": [],
      "growth": {
        "status": "scored",
        "resolution": 10,
        "coverage": 12,
        "depth_avg": 2.5,
        "metrics": {
          "clarity": 2,
          "structure": 2,
          "evidence": 2,
          "output_quality": 3,
          "outcome_quality": 0,
          "decision_thinking": 0
        }
      }
    },
    {
      "name": "양은정",
      "team": "운영팀",
      "task_count": 32,
      "completion_rate": 44,
      "categories": {
        "실행": 11,
        "관리": 9,
        "커뮤니케이션": 6,
        "기타": 3,
        "기획": 2,
        "리서치": 1
      },
      "blockers": [
        "스피커 연결 잭 손상",
        "업무 진행에 있어서 금방 풀리지 않고 과한 부담감에 업무에 있어 효율이 떨어지는 것을 경험했어",
        "-올드타운 창고 정리 일정 픽스- 윤성수 실장님 측과 함께 진행",
        "특이사항 - 100메가로 신청 하였으나, 건물 환경에 따른 설치 가능 여부가 결정 되는 와중 현재 설치 예정"
      ],
      "tools": [],
      "open_decisions": [
        "관사 16 철거 작업 인력 지출결의서 1차 승인 완료  은정 초과근무 4시간"
      ],
      "growth": {
        "status": "scored",
        "resolution": 42,
        "coverage": 62,
        "depth_avg": 2.0,
        "metrics": {
          "clarity": 2,
          "structure": 2,
          "evidence": 2,
          "output_quality": 2,
          "outcome_quality": 0,
          "decision_thinking": 0
        }
      }
    },
    {
      "name": "윤혜정",
      "team": "운영팀",
      "task_count": 30,
      "completion_rate": 80,
      "categories": {
        "커뮤니케이션": 12,
        "기획": 10,
        "실행": 4,
        "리서치": 2,
        "교육": 1,
        "관리": 1
      },
      "blockers": [],
      "tools": [
        "챗지피티"
      ],
      "open_decisions": [],
      "growth": {
        "status": "scored",
        "resolution": 58,
        "coverage": 88,
        "depth_avg": 2.0,
        "metrics": {
          "clarity": 2,
          "structure": 2,
          "evidence": 2,
          "output_quality": 2,
          "outcome_quality": 2,
          "decision_thinking": 0
        }
      }
    }
  ],
  "assignments": [
    {
      "date": "2026-07-08",
      "project": "봉은사",
      "team": "경영",
      "assignee": "최원석",
      "task": "상세BM리서치 팔로우업 진행",
      "deadline": "",
      "status": "미착수",
      "priority": "일반"
    },
    {
      "date": "2026-07-08",
      "project": "세스크멘슬",
      "team": "경영",
      "assignee": "최원석",
      "task": "세스크멘슬 브랜드 개발 방향 구체화",
      "deadline": "",
      "status": "미착수",
      "priority": "긴급"
    },
    {
      "date": "2026-07-08",
      "project": "세스크멘슬",
      "team": "공간팀",
      "assignee": "전제훈",
      "task": "공간디자인 방향성 논의",
      "deadline": "",
      "status": "미착수",
      "priority": "긴급"
    },
    {
      "date": "2026-07-08",
      "project": "여수섬박람회",
      "team": "공간팀",
      "assignee": "전제훈",
      "task": "여수 섬박람회 공간 방향성 확정",
      "deadline": "",
      "status": "미착수",
      "priority": "긴급"
    },
    {
      "date": "2026-07-08",
      "project": "여수섬박람회",
      "team": "운영팀",
      "assignee": "윤혜정",
      "task": "여수 섬박람회 착수보고 팔로우업 준비",
      "deadline": "",
      "status": "미착수",
      "priority": "일반"
    }
  ],
  "unmatched_names": [],
  "generated_at": "2026-07-08 21:35"
}